django_informixdb_vault_dev/__init__.py
django_informixdb_vault_dev/base.py
django_informixdb_vault_dev/version.py
django_informixdb_vault_dev-0.1.dev13.dist-info/LICENSE
django_informixdb_vault_dev-0.1.dev13.dist-info/METADATA
django_informixdb_vault_dev-0.1.dev13.dist-info/WHEEL
django_informixdb_vault_dev-0.1.dev13.dist-info/top_level.txt
django_informixdb_vault_dev-0.1.dev13.dist-info/RECORD
